setup.py
tapioca_github/__init__.py
tapioca_github/resource_mapping.py
tapioca_github/tapioca_github.py
tapioca_github_vinta.egg-info/PKG-INFO
tapioca_github_vinta.egg-info/SOURCES.txt
tapioca_github_vinta.egg-info/dependency_links.txt
tapioca_github_vinta.egg-info/not-zip-safe
tapioca_github_vinta.egg-info/requires.txt
tapioca_github_vinta.egg-info/top_level.txt