Metadata-Version: 1.1
Name: tapioca-github-vinta
Version: 0.3
Summary: Github API wrapper using tapioca
Home-page: https://github.com/vintasoftware/tapioca-github
Author: Gileno Filho
Author-email: contato@gilenofilho.com.br
License: MIT
Keywords: tapioca-github
Platform: UNKNOWN
Classifier: Development Status :: 5 - Production/Stable
Classifier: Intended Audience :: Developers
Classifier: License :: OSI Approved :: MIT License
Classifier: Natural Language :: English
Classifier: Programming Language :: Python :: 2
Classifier: Programming Language :: Python :: 3
